modepy/__init__.py
modepy/matrices.py
modepy/modal_decay.py
modepy/modes.py
modepy/nodes.py
modepy/py.typed
modepy/shapes.py
modepy/spaces.py
modepy/tools.py
modepy/typing.py
modepy/version.py
modepy/quadrature/__init__.py
modepy/quadrature/clenshaw_curtis.py
modepy/quadrature/construction.py
modepy/quadrature/grundmann_moeller.py
modepy/quadrature/jacobi_gauss.py
modepy/quadrature/jaskowiec_sukumar.py
modepy/quadrature/jaskowiec_sukumar_tet_data.py
modepy/quadrature/vioreanu_rokhlin.py
modepy/quadrature/vr_quad_data_tet.py
modepy/quadrature/vr_quad_data_tri.py
modepy/quadrature/witherden_vincent.py
modepy/quadrature/witherden_vincent_quad_data.py
modepy/quadrature/xg_quad_data.py
modepy/quadrature/xiao_gimbutas.py
modepy/test/__init__.py
modepy/test/test_matrices.py
modepy/test/test_modes.py
modepy/test/test_nodes.py
modepy/test/test_quad_construction.py
modepy/test/test_quadrature.py
modepy/test/test_tools.py
modepy-2026.1.dist-info/METADATA
modepy-2026.1.dist-info/WHEEL
modepy-2026.1.dist-info/licenses/LICENSE
modepy-2026.1.dist-info/RECORD
