Metadata-Version: 2.4
Name: modepy
Version: 2026.1
Summary: Modes and nodes for high-order methods
Project-URL: Documentation, https://documen.tician.de/modepy
Project-URL: Homepage, https://mathema.tician.de/software/modepy
Project-URL: Repository, https://github.com/inducer/modepy
Author-email: Andreas Kloeckner <inform@tiker.net>
License-Expression: MIT
License-File: LICENSE
Classifier: Development Status :: 3 - Alpha
Classifier: Intended Audience :: Developers
Classifier: Intended Audience :: Other Audience
Classifier: Intended Audience :: Science/Research
Classifier: Natural Language :: English
Classifier: Programming Language :: Python
Classifier: Programming Language :: Python :: 3 :: Only
Classifier: Topic :: Scientific/Engineering
Classifier: Topic :: Scientific/Engineering :: Information Analysis
Classifier: Topic :: Scientific/Engineering :: Mathematics
Classifier: Topic :: Scientific/Engineering :: Visualization
Classifier: Topic :: Software Development :: Libraries
Classifier: Topic :: Utilities
Requires-Python: >=3.10
Requires-Dist: numpy
Requires-Dist: pymbolic>=2024.2
Requires-Dist: pytools
Requires-Dist: typing-extensions>=4.1
Provides-Extra: doc
Requires-Dist: furo; extra == 'doc'
Requires-Dist: sphinx-copybutton; extra == 'doc'
Requires-Dist: sphinx>=4; extra == 'doc'
Provides-Extra: test
Requires-Dist: basedpyright; extra == 'test'
Requires-Dist: pytest; extra == 'test'
Requires-Dist: ruff; extra == 'test'
